atsphinx/audioplayer/__init__.py
atsphinx/audioplayer/nodes.py
atsphinx/audioplayer/py.typed
atsphinx_audioplayer-0.2.1.dist-info/METADATA
atsphinx_audioplayer-0.2.1.dist-info/WHEEL
atsphinx_audioplayer-0.2.1.dist-info/licenses/LICENSE
atsphinx_audioplayer-0.2.1.dist-info/RECORD
